confini/__init__.py
confini/config.py
confini/error.py
confini/runnable/dump.py
confini-0.3.5.dist-info/LICENSE.txt
confini-0.3.5.dist-info/METADATA
confini-0.3.5.dist-info/WHEEL
confini-0.3.5.dist-info/entry_points.txt
confini-0.3.5.dist-info/top_level.txt
confini-0.3.5.dist-info/RECORD
