Metadata-Version: 2.1
Name: confini
Version: 0.3.5
Summary: Parse, verify and merge all ini files in a single directory
Home-page: https://gitlab.com/nolash/python-confini
Author: Louis Holbrook
Author-email: dev@holbrook.no
License: GPL3
Platform: UNKNOWN
Classifier: Environment :: No Input/Output (Daemon)
Classifier: Programming Language :: Python :: 3
Classifier: Operating System :: OS Independent
Classifier: Development Status :: 3 - Alpha
Classifier: Intended Audience :: Developers
Classifier: Topic :: Software Development :: Libraries
Classifier: License :: OSI Approved :: GNU General Public License v3 or later (GPLv3+)
Requires-Dist: python-gnupg (<0.5.0,>=0.4.6)
